{
  "id": "251109-0780d5e4-1206-43dc-af8c-f38557e582af",
  "is_detailed": true,
  "game_type": 3,
  "game_date": "2025-11-09T09:31:40+00:00",
  "session_players": [
    {
      "seat": 0,
      "username": "YuuNecro",
      "final_ranking": 1,
      "final_score": 44100,
      "final_point": 34.1
    },
    {
      "seat": 1,
      "username": "Eucliwood",
      "final_ranking": 2,
      "final_score": 41000,
      "final_point": 21.0
    },
    {
      "seat": 2,
      "username": "Hellscythe",
      "final_ranking": 3,
      "final_score": 18700,
      "final_point": -11.3
    },
    {
      "seat": 3,
      "username": "Player4",
      "final_ranking": 4,
      "final_score": -3800,
      "final_point": -43.8
    }
  ],
  "round_records": [
    {
      "idx": 0,
      "wind": 0,
      "dealer": 0,
      "honba": 0,
      "kyotaku": 0,
      "renchan": true,
      "ryukyoku": true,
      "players": [
        {
          "seat": 0,
          "win": false,
          "tsumo": false,
          "lose": false,
          "fuulu": false,
          "reach": true,
          "tenpai": true,
          "fan": 0,
          "fu": 0,
          "startingscore": 25000,
          "deltascore": 2000,
          "endingscore": 27000
        },
        {
          "seat": 1,
          "win": false,
          "tsumo": false,
          "lose": false,
          "fuulu": false,
          "reach": false,
          "tenpai": false,
          "fan": 0,
          "fu": 0,
          "startingscore": 25000,
          "deltascore": -1000,
          "endingscore": 24000
        },
        {
          "seat": 2,
          "win": false,
          "tsumo": false,
          "lose": false,
          "fuulu": true,
          "reach": false,
          "tenpai": false,
          "fan": 0,
          "fu": 0,
          "startingscore": 25000,
          "deltascore": -1000,
          "endingscore": 24000
        },
        {
          "seat": 3,
          "win": false,
          "tsumo": false,
          "lose": false,
          "fuulu": true,
          "reach": false,
          "tenpai": false,
          "fan": 0,
          "fu": 0,
          "startingscore": 25000,
          "deltascore": -1000,
          "endingscore": 24000
        }
      ]
    },
    {
      "idx": 1,
      "wind": 0,
      "dealer": 0,
      "honba": 1,
      "kyotaku": 1,
      "renchan": true,
      "ryukyoku": false,
      "players": [
        {
          "seat": 0,
          "win": true,
          "tsumo": false,
          "lose": false,
          "fuulu": false,
          "reach": true,
          "tenpai": false,
          "fan": 3,
          "fu": 30,
          "startingscore": 27000,
          "deltascore": 8100,
          "endingscore": 35100
        },
        {
          "seat": 1,
          "win": true,
          "tsumo": false,
          "lose": false,
          "fuulu": false,
          "reach": true,
          "tenpai": false,
          "fan": 6,
          "fu": 40,
          "startingscore": 24000,
          "deltascore": 11000,
          "endingscore": 35000
        },
        {
          "seat": 2,
          "win": false,
          "tsumo": false,
          "lose": true,
          "fuulu": false,
          "reach": false,
          "tenpai": false,
          "fan": 0,
          "fu": 0,
          "startingscore": 24000,
          "deltascore": -18100,
          "endingscore": 5900
        },
        {
          "seat": 3,
          "win": false,
          "tsumo": false,
          "lose": false,
          "fuulu": true,
          "reach": false,
          "tenpai": false,
          "fan": 0,
          "fu": 0,
          "startingscore": 24000,
          "deltascore": 0,
          "endingscore": 24000
        }
      ]
    },
    {
      "idx": 2,
      "wind": 0,
      "dealer": 0,
      "honba": 2,
      "kyotaku": 0,
      "renchan": false,
      "ryukyoku": false,
      "players": [
        {
          "seat": 0,
          "win": false,
          "tsumo": false,
          "lose": false,
          "fuulu": false,
          "reach": false,
          "tenpai": false,
          "fan": 0,
          "fu": 0,
          "startingscore": 35100,
          "deltascore": -1800,
          "endingscore": 33300
        },
        {
          "seat": 1,
          "win": false,
          "tsumo": false,
          "lose": false,
          "fuulu": true,
          "reach": false,
          "tenpai": false,
          "fan": 0,
          "fu": 0,
          "startingscore": 35000,
          "deltascore": -1000,
          "endingscore": 34000
        },
        {
          "seat": 2,
          "win": false,
          "tsumo": false,
          "lose": false,
          "fuulu": false,
          "reach": false,
          "tenpai": false,
          "fan": 0,
          "fu": 0,
          "startingscore": 5900,
          "deltascore": -1000,
          "endingscore": 4900
        },
        {
          "seat": 3,
          "win": true,
          "tsumo": true,
          "lose": false,
          "fuulu": true,
          "reach": false,
          "tenpai": false,
          "fan": 2,
          "fu": 50,
          "startingscore": 24000,
          "deltascore": 3800,
          "endingscore": 27800
        }
      ]
    },
    {
      "idx": 3,
      "wind": 0,
      "dealer": 1,
      "honba": 0,
      "kyotaku": 0,
      "renchan": true,
      "ryukyoku": false,
      "players": [
        {
          "seat": 0,
          "win": false,
          "tsumo": false,
          "lose": false,
          "fuulu": false,
          "reach": false,
          "tenpai": false,
          "fan": 0,
          "fu": 0,
          "startingscore": 33300,
          "deltascore": 0,
          "endingscore": 33300
        },
        {
          "seat": 1,
          "win": true,
          "tsumo": false,
          "lose": false,
          "fuulu": false,
          "reach": true,
          "tenpai": false,
          "fan": 4,
          "fu": 30,
          "startingscore": 34000,
          "deltascore": 11600,
          "endingscore": 45600
        },
        {
          "seat": 2,
          "win": false,
          "tsumo": false,
          "lose": false,
          "fuulu": false,
          "reach": false,
          "tenpai": false,
          "fan": 0,
          "fu": 0,
          "startingscore": 4900,
          "deltascore": 0,
          "endingscore": 4900
        },
        {
          "seat": 3,
          "win": false,
          "tsumo": false,
          "lose": true,
          "fuulu": true,
          "reach": false,
          "tenpai": false,
          "fan": 0,
          "fu": 0,
          "startingscore": 27800,
          "deltascore": -11600,
          "endingscore": 16200
        }
      ]
    },
    {
      "idx": 4,
      "wind": 0,
      "dealer": 1,
      "honba": 1,
      "kyotaku": 0,
      "renchan": false,
      "ryukyoku": false,
      "players": [
        {
          "seat": 0,
          "win": true,
          "tsumo": false,
          "lose": false,
          "fuulu": true,
          "reach": false,
          "tenpai": false,
          "fan": 4,
          "fu": 50,
          "startingscore": 33300,
          "deltascore": 8300,
          "endingscore": 41600
        },
        {
          "seat": 1,
          "win": false,
          "tsumo": false,
          "lose": false,
          "fuulu": false,
          "reach": false,
          "tenpai": false,
          "fan": 0,
          "fu": 0,
          "startingscore": 45600,
          "deltascore": 0,
          "endingscore": 45600
        },
        {
          "seat": 2,
          "win": false,
          "tsumo": false,
          "lose": false,
          "fuulu": false,
          "reach": false,
          "tenpai": false,
          "fan": 0,
          "fu": 0,
          "startingscore": 4900,
          "deltascore": 0,
          "endingscore": 4900
        },
        {
          "seat": 3,
          "win": false,
          "tsumo": false,
          "lose": true,
          "fuulu": true,
          "reach": false,
          "tenpai": false,
          "fan": 0,
          "fu": 0,
          "startingscore": 16200,
          "deltascore": -8300,
          "endingscore": 7900
        }
      ]
    },
    {
      "idx": 5,
      "wind": 0,
      "dealer": 2,
      "honba": 0,
      "kyotaku": 0,
      "renchan": false,
      "ryukyoku": false,
      "players": [
        {
          "seat": 0,
          "win": false,
          "tsumo": false,
          "lose": false,
          "fuulu": false,
          "reach": false,
          "tenpai": false,
          "fan": 0,
          "fu": 0,
          "startingscore": 41600,
          "deltascore": 0,
          "endingscore": 41600
        },
        {
          "seat": 1,
          "win": false,
          "tsumo": false,
          "lose": true,
          "fuulu": false,
          "reach": false,
          "tenpai": false,
          "fan": 0,
          "fu": 0,
          "startingscore": 45600,
          "deltascore": -2600,
          "endingscore": 43000
        },
        {
          "seat": 2,
          "win": false,
          "tsumo": false,
          "lose": false,
          "fuulu": false,
          "reach": false,
          "tenpai": false,
          "fan": 0,
          "fu": 0,
          "startingscore": 4900,
          "deltascore": 0,
          "endingscore": 4900
        },
        {
          "seat": 3,
          "win": true,
          "tsumo": false,
          "lose": false,
          "fuulu": false,
          "reach": false,
          "tenpai": false,
          "fan": 2,
          "fu": 40,
          "startingscore": 7900,
          "deltascore": 2600,
          "endingscore": 10500
        }
      ]
    },
    {
      "idx": 6,
      "wind": 0,
      "dealer": 3,
      "honba": 0,
      "kyotaku": 0,
      "renchan": true,
      "ryukyoku": false,
      "players": [
        {
          "seat": 0,
          "win": false,
          "tsumo": false,
          "lose": true,
          "fuulu": false,
          "reach": false,
          "tenpai": false,
          "fan": 0,
          "fu": 0,
          "startingscore": 41600,
          "deltascore": -5800,
          "endingscore": 35800
        },
        {
          "seat": 1,
          "win": false,
          "tsumo": false,
          "lose": false,
          "fuulu": false,
          "reach": false,
          "tenpai": false,
          "fan": 0,
          "fu": 0,
          "startingscore": 43000,
          "deltascore": 0,
          "endingscore": 43000
        },
        {
          "seat": 2,
          "win": false,
          "tsumo": false,
          "lose": false,
          "fuulu": false,
          "reach": false,
          "tenpai": false,
          "fan": 0,
          "fu": 0,
          "startingscore": 4900,
          "deltascore": 0,
          "endingscore": 4900
        },
        {
          "seat": 3,
          "win": true,
          "tsumo": false,
          "lose": false,
          "fuulu": true,
          "reach": false,
          "tenpai": false,
          "fan": 3,
          "fu": 30,
          "startingscore": 10500,
          "deltascore": 5800,
          "endingscore": 16300
        }
      ]
    },
    {
      "idx": 7,
      "wind": 0,
      "dealer": 3,
      "honba": 1,
      "kyotaku": 0,
      "renchan": true,
      "ryukyoku": true,
      "players": [
        {
          "seat": 0,
          "win": false,
          "tsumo": false,
          "lose": false,
          "fuulu": false,
          "reach": false,
          "tenpai": false,
          "fan": 0,
          "fu": 0,
          "startingscore": 35800,
          "deltascore": -1500,
          "endingscore": 34300
        },
        {
          "seat": 1,
          "win": false,
          "tsumo": false,
          "lose": false,
          "fuulu": false,
          "reach": false,
          "tenpai": false,
          "fan": 0,
          "fu": 0,
          "startingscore": 43000,
          "deltascore": -1500,
          "endingscore": 41500
        },
        {
          "seat": 2,
          "win": false,
          "tsumo": false,
          "lose": false,
          "fuulu": false,
          "reach": true,
          "tenpai": true,
          "fan": 0,
          "fu": 0,
          "startingscore": 4900,
          "deltascore": 500,
          "endingscore": 5400
        },
        {
          "seat": 3,
          "win": false,
          "tsumo": false,
          "lose": false,
          "fuulu": false,
          "reach": true,
          "tenpai": true,
          "fan": 0,
          "fu": 0,
          "startingscore": 16300,
          "deltascore": 500,
          "endingscore": 16800
        }
      ]
    },
    {
      "idx": 8,
      "wind": 0,
      "dealer": 3,
      "honba": 2,
      "kyotaku": 2,
      "renchan": false,
      "ryukyoku": false,
      "players": [
        {
          "seat": 0,
          "win": true,
          "tsumo": true,
          "lose": false,
          "fuulu": false,
          "reach": true,
          "tenpai": false,
          "fan": 5,
          "fu": 20,
          "startingscore": 34300,
          "deltascore": 10600,
          "endingscore": 44900
        },
        {
          "seat": 1,
          "win": false,
          "tsumo": false,
          "lose": false,
          "fuulu": false,
          "reach": false,
          "tenpai": false,
          "fan": 0,
          "fu": 0,
          "startingscore": 41500,
          "deltascore": -2200,
          "endingscore": 39300
        },
        {
          "seat": 2,
          "win": false,
          "tsumo": false,
          "lose": false,
          "fuulu": false,
          "reach": false,
          "tenpai": false,
          "fan": 0,
          "fu": 0,
          "startingscore": 5400,
          "deltascore": -2200,
          "endingscore": 3200
        },
        {
          "seat": 3,
          "win": false,
          "tsumo": false,
          "lose": false,
          "fuulu": true,
          "reach": false,
          "tenpai": false,
          "fan": 0,
          "fu": 0,
          "startingscore": 16800,
          "deltascore": -4200,
          "endingscore": 12600
        }
      ]
    },
    {
      "idx": 9,
      "wind": 1,
      "dealer": 0,
      "honba": 0,
      "kyotaku": 0,
      "renchan": false,
      "ryukyoku": false,
      "players": [
        {
          "seat": 0,
          "win": false,
          "tsumo": false,
          "lose": false,
          "fuulu": true,
          "reach": false,
          "tenpai": false,
          "fan": 0,
          "fu": 0,
          "startingscore": 44900,
          "deltascore": -6000,
          "endingscore": 38900
        },
        {
          "seat": 1,
          "win": false,
          "tsumo": false,
          "lose": false,
          "fuulu": false,
          "reach": false,
          "tenpai": false,
          "fan": 0,
          "fu": 0,
          "startingscore": 39300,
          "deltascore": -3000,
          "endingscore": 36300
        },
        {
          "seat": 2,
          "win": true,
          "tsumo": true,
          "lose": false,
          "fuulu": false,
          "reach": true,
          "tenpai": false,
          "fan": 6,
          "fu": 30,
          "startingscore": 3200,
          "deltascore": 12000,
          "endingscore": 15200
        },
        {
          "seat": 3,
          "win": false,
          "tsumo": false,
          "lose": false,
          "fuulu": true,
          "reach": false,
          "tenpai": false,
          "fan": 0,
          "fu": 0,
          "startingscore": 12600,
          "deltascore": -3000,
          "endingscore": 9600
        }
      ]
    },
    {
      "idx": 10,
      "wind": 1,
      "dealer": 1,
      "honba": 0,
      "kyotaku": 0,
      "renchan": false,
      "ryukyoku": false,
      "players": [
        {
          "seat": 0,
          "win": true,
          "tsumo": false,
          "lose": false,
          "fuulu": false,
          "reach": false,
          "tenpai": false,
          "fan": 4,
          "fu": 30,
          "startingscore": 38900,
          "deltascore": 7700,
          "endingscore": 46600
        },
        {
          "seat": 1,
          "win": false,
          "tsumo": false,
          "lose": false,
          "fuulu": false,
          "reach": false,
          "tenpai": false,
          "fan": 0,
          "fu": 0,
          "startingscore": 36300,
          "deltascore": 0,
          "endingscore": 36300
        },
        {
          "seat": 2,
          "win": false,
          "tsumo": false,
          "lose": false,
          "fuulu": false,
          "reach": false,
          "tenpai": false,
          "fan": 0,
          "fu": 0,
          "startingscore": 15200,
          "deltascore": 0,
          "endingscore": 15200
        },
        {
          "seat": 3,
          "win": false,
          "tsumo": false,
          "lose": true,
          "fuulu": false,
          "reach": false,
          "tenpai": false,
          "fan": 0,
          "fu": 0,
          "startingscore": 9600,
          "deltascore": -7700,
          "endingscore": 1900
        }
      ]
    },
    {
      "idx": 11,
      "wind": 1,
      "dealer": 2,
      "honba": 0,
      "kyotaku": 0,
      "renchan": true,
      "ryukyoku": true,
      "players": [
        {
          "seat": 0,
          "win": false,
          "tsumo": false,
          "lose": false,
          "fuulu": true,
          "reach": false,
          "tenpai": true,
          "fan": 0,
          "fu": 0,
          "startingscore": 46600,
          "deltascore": 1500,
          "endingscore": 48100
        },
        {
          "seat": 1,
          "win": false,
          "tsumo": false,
          "lose": false,
          "fuulu": false,
          "reach": false,
          "tenpai": false,
          "fan": 0,
          "fu": 0,
          "startingscore": 36300,
          "deltascore": -1500,
          "endingscore": 34800
        },
        {
          "seat": 2,
          "win": false,
          "tsumo": false,
          "lose": false,
          "fuulu": true,
          "reach": false,
          "tenpai": true,
          "fan": 0,
          "fu": 0,
          "startingscore": 15200,
          "deltascore": 1500,
          "endingscore": 16700
        },
        {
          "seat": 3,
          "win": false,
          "tsumo": false,
          "lose": false,
          "fuulu": false,
          "reach": false,
          "tenpai": false,
          "fan": 0,
          "fu": 0,
          "startingscore": 1900,
          "deltascore": -1500,
          "endingscore": 400
        }
      ]
    },
    {
      "idx": 12,
      "wind": 1,
      "dealer": 2,
      "honba": 1,
      "kyotaku": 0,
      "renchan": true,
      "ryukyoku": true,
      "players": [
        {
          "seat": 0,
          "win": false,
          "tsumo": false,
          "lose": false,
          "fuulu": false,
          "reach": false,
          "tenpai": true,
          "fan": 0,
          "fu": 0,
          "startingscore": 48100,
          "deltascore": 1000,
          "endingscore": 49100
        },
        {
          "seat": 1,
          "win": false,
          "tsumo": false,
          "lose": false,
          "fuulu": false,
          "reach": false,
          "tenpai": false,
          "fan": 0,
          "fu": 0,
          "startingscore": 34800,
          "deltascore": -3000,
          "endingscore": 31800
        },
        {
          "seat": 2,
          "win": false,
          "tsumo": false,
          "lose": false,
          "fuulu": true,
          "reach": false,
          "tenpai": true,
          "fan": 0,
          "fu": 0,
          "startingscore": 16700,
          "deltascore": 1000,
          "endingscore": 17700
        },
        {
          "seat": 3,
          "win": false,
          "tsumo": false,
          "lose": false,
          "fuulu": true,
          "reach": false,
          "tenpai": true,
          "fan": 0,
          "fu": 0,
          "startingscore": 400,
          "deltascore": 1000,
          "endingscore": 1400
        }
      ]
    },
    {
      "idx": 13,
      "wind": 1,
      "dealer": 2,
      "honba": 2,
      "kyotaku": 0,
      "renchan": true,
      "ryukyoku": true,
      "players": [
        {
          "seat": 0,
          "win": false,
          "tsumo": false,
          "lose": false,
          "fuulu": false,
          "reach": false,
          "tenpai": false,
          "fan": 0,
          "fu": 0,
          "startingscore": 49100,
          "deltascore": -1500,
          "endingscore": 47600
        },
        {
          "seat": 1,
          "win": false,
          "tsumo": false,
          "lose": false,
          "fuulu": false,
          "reach": false,
          "tenpai": false,
          "fan": 0,
          "fu": 0,
          "startingscore": 31800,
          "deltascore": -1500,
          "endingscore": 30300
        },
        {
          "seat": 2,
          "win": false,
          "tsumo": false,
          "lose": false,
          "fuulu": true,
          "reach": false,
          "tenpai": true,
          "fan": 0,
          "fu": 0,
          "startingscore": 17700,
          "deltascore": 1500,
          "endingscore": 19200
        },
        {
          "seat": 3,
          "win": false,
          "tsumo": false,
          "lose": false,
          "fuulu": true,
          "reach": false,
          "tenpai": true,
          "fan": 0,
          "fu": 0,
          "startingscore": 1400,
          "deltascore": 1500,
          "endingscore": 2900
        }
      ]
    },
    {
      "idx": 14,
      "wind": 1,
      "dealer": 2,
      "honba": 3,
      "kyotaku": 0,
      "renchan": true,
      "ryukyoku": true,
      "players": [
        {
          "seat": 0,
          "win": false,
          "tsumo": false,
          "lose": false,
          "fuulu": true,
          "reach": false,
          "tenpai": false,
          "fan": 0,
          "fu": 0,
          "startingscore": 47600,
          "deltascore": -1500,
          "endingscore": 46100
        },
        {
          "seat": 1,
          "win": false,
          "tsumo": false,
          "lose": false,
          "fuulu": true,
          "reach": false,
          "tenpai": false,
          "fan": 0,
          "fu": 0,
          "startingscore": 30300,
          "deltascore": -1500,
          "endingscore": 28800
        },
        {
          "seat": 2,
          "win": false,
          "tsumo": false,
          "lose": false,
          "fuulu": true,
          "reach": false,
          "tenpai": true,
          "fan": 0,
          "fu": 0,
          "startingscore": 19200,
          "deltascore": 1500,
          "endingscore": 20700
        },
        {
          "seat": 3,
          "win": false,
          "tsumo": false,
          "lose": false,
          "fuulu": false,
          "reach": true,
          "tenpai": true,
          "fan": 0,
          "fu": 0,
          "startingscore": 2900,
          "deltascore": 500,
          "endingscore": 3400
        }
      ]
    },
    {
      "idx": 15,
      "wind": 1,
      "dealer": 2,
      "honba": 4,
      "kyotaku": 1,
      "renchan": false,
      "ryukyoku": false,
      "players": [
        {
          "seat": 0,
          "win": false,
          "tsumo": false,
          "lose": false,
          "fuulu": false,
          "reach": false,
          "tenpai": false,
          "fan": 0,
          "fu": 0,
          "startingscore": 46100,
          "deltascore": 0,
          "endingscore": 46100
        },
        {
          "seat": 1,
          "win": true,
          "tsumo": false,
          "lose": false,
          "fuulu": true,
          "reach": false,
          "tenpai": false,
          "fan": 2,
          "fu": 30,
          "startingscore": 28800,
          "deltascore": 4200,
          "endingscore": 33000
        },
        {
          "seat": 2,
          "win": false,
          "tsumo": false,
          "lose": false,
          "fuulu": true,
          "reach": false,
          "tenpai": false,
          "fan": 0,
          "fu": 0,
          "startingscore": 20700,
          "deltascore": 0,
          "endingscore": 20700
        },
        {
          "seat": 3,
          "win": false,
          "tsumo": false,
          "lose": true,
          "fuulu": false,
          "reach": false,
          "tenpai": false,
          "fan": 0,
          "fu": 0,
          "startingscore": 3400,
          "deltascore": -3200,
          "endingscore": 200
        }
      ]
    },
    {
      "idx": 16,
      "wind": 1,
      "dealer": 3,
      "honba": 0,
      "kyotaku": 0,
      "renchan": false,
      "ryukyoku": false,
      "players": [
        {
          "seat": 0,
          "win": false,
          "tsumo": false,
          "lose": false,
          "fuulu": true,
          "reach": false,
          "tenpai": false,
          "fan": 0,
          "fu": 0,
          "startingscore": 46100,
          "deltascore": -2000,
          "endingscore": 44100
        },
        {
          "seat": 1,
          "win": true,
          "tsumo": true,
          "lose": false,
          "fuulu": false,
          "reach": true,
          "tenpai": false,
          "fan": 5,
          "fu": 30,
          "startingscore": 33000,
          "deltascore": 8000,
          "endingscore": 41000
        },
        {
          "seat": 2,
          "win": false,
          "tsumo": false,
          "lose": false,
          "fuulu": true,
          "reach": false,
          "tenpai": false,
          "fan": 0,
          "fu": 0,
          "startingscore": 20700,
          "deltascore": -2000,
          "endingscore": 18700
        },
        {
          "seat": 3,
          "win": false,
          "tsumo": false,
          "lose": false,
          "fuulu": true,
          "reach": false,
          "tenpai": false,
          "fan": 0,
          "fu": 0,
          "startingscore": 200,
          "deltascore": -4000,
          "endingscore": -3800
        }
      ]
    }
  ]
}